meditate/__init__.py
meditate/data/bell.wav
vipassana_timer-1.1.dist-info/LICENSE
vipassana_timer-1.1.dist-info/METADATA
vipassana_timer-1.1.dist-info/WHEEL
vipassana_timer-1.1.dist-info/entry_points.txt
vipassana_timer-1.1.dist-info/top_level.txt
vipassana_timer-1.1.dist-info/RECORD
