Metadata-Version: 2.1
Name: vipassana-timer
Version: 1.1
Summary: A small meditation timer for vipassana
Home-page: https://github.com/toxicologist/vipassana-timer
Author: toxicologist
Author-email: toxiccologist@gmail.com
License: MIT
Project-URL: Bug Tracker, https://github.com/toxicologist/vipassana-timer/issues
Keywords: meditation,vipassana,timer,countdown
Classifier: Programming Language :: Python :: 3
Classifier: License :: OSI Approved :: MIT License
Classifier: Operating System :: OS Independent
Requires-Python: >=3.7
License-File: LICENSE
Requires-Dist: argparse
Requires-Dist: humanize
Requires-Dist: playsound
